Metadata-Version: 1.0
Name: pymephisto
Version: 0.1
Summary: Load PTW Mephisto files
Home-page: UNKNOWN
Author: Simon Biggs
Author-email: mail@simonbiggs.net
License: AGPL3+
Platform: UNKNOWN
